ad_rss_map_integration/__init__.py
ad_rss_map_integration/ad_rss_map_integration_python312.so
ad_rss_map_integration.libs/libad_map_access-3ccdca63.so
ad_rss_map_integration.libs/libad_map_opendrive_reader-f6f0a407.so
ad_rss_map_integration.libs/libad_physics-25c66a14.so
ad_rss_map_integration.libs/libad_rss-45775ec1.so
ad_rss_map_integration.libs/libad_rss_map_integration-cecc8334.so
ad_rss_map_integration.libs/libboost_filesystem-2eec8050.so.1.83.0
ad_rss_map_integration.libs/libboost_program_options-8eb24a48.so.1.83.0
ad_rss_map_integration.libs/libboost_python312-2248061d.so.1.83.0
ad_rss_map_integration.libs/libfmt-d463bedd.so.8.1.1
ad_rss_map_integration.libs/libproj-6e07a527.so.12.0.0
ad_rss_map_integration.libs/libpugixml-fdb08e1d.so.1.12
ad_rss_map_integration.libs/libspdlog-1de96ba8.so.1.9.2
ad_rss_map_integration-5.0.0.dist-info/METADATA
ad_rss_map_integration-5.0.0.dist-info/WHEEL
ad_rss_map_integration-5.0.0.dist-info/top_level.txt
ad_rss_map_integration-5.0.0.dist-info/RECORD
